gkbus/__init__.py
gkbus/exceptions.py
gkbus/interface/CanInterface.py
gkbus/interface/Interface.py
gkbus/interface/KLineInterface.py
gkbus/interface/__init__.py
gkbus/interface/kline/KLineSerial.py
gkbus/interface/kline/__init__.py
gkbus/kwp/KWPCommand.py
gkbus/kwp/KWPNegativeStatus.py
gkbus/kwp/KWPResponse.py
gkbus/kwp/__init__.py
gkbus/kwp/commands.py
gkbus/kwp/enums.py
gkbus_test-0.2.7.dist-info/LICENSE
gkbus_test-0.2.7.dist-info/METADATA
gkbus_test-0.2.7.dist-info/WHEEL
gkbus_test-0.2.7.dist-info/top_level.txt
gkbus_test-0.2.7.dist-info/RECORD
